cwtags/__init__.py
cwtags/__pkginfo__.py
cwtags/tag.py
cwtags/tagbuilder.py
cwtags-1.2.3.dist-info/METADATA
cwtags-1.2.3.dist-info/WHEEL
cwtags-1.2.3.dist-info/top_level.txt
cwtags-1.2.3.dist-info/RECORD
