Metadata-Version: 2.1
Name: cwtags
Version: 1.2.3
Summary: UNKNOWN
Home-page: http://www.cubicweb.org/project/cwtags
Author: Logilab
Author-email: contact@logilab.fr
License: GPL
Platform: UNKNOWN
Classifier: Environment :: Web Environment
Classifier: Intended Audience :: Developers
Classifier: Topic :: Software Development :: Libraries :: Python Modules
Classifier: Topic :: Text Processing :: Markup :: HTML
Classifier: Programming Language :: Python
Classifier: Operating System :: OS Independent
Requires-Dist: logilab-common
